pyroadacoustics/__init__.py
pyroadacoustics/delayLine.py
pyroadacoustics/environment.py
pyroadacoustics/material.py
pyroadacoustics/materials.json
pyroadacoustics/microphoneArray.py
pyroadacoustics/simulatorManager.py
pyroadacoustics/soundSource.py
pyroadacoustics-1.1.0.dist-info/LICENSE
pyroadacoustics-1.1.0.dist-info/METADATA
pyroadacoustics-1.1.0.dist-info/WHEEL
pyroadacoustics-1.1.0.dist-info/top_level.txt
pyroadacoustics-1.1.0.dist-info/RECORD
