Metadata-Version: 2.1
Name: pyroadacoustics
Version: 1.1.0
Summary: A package for simulating the sound propagation in a road scenario
Author-email: Stefano Damiano <stefano.damiano@esat.kuleuven.be>
License: GNU GENERAL PUBLIC LICENSE
Project-URL: Repository, https://github.com/steDamiano/pyroadacoustics
Keywords: outdoor acoustics,automotive,signal processing,traffic sound simulation
Classifier: Development Status :: 4 - Beta
Classifier: Intended Audience :: Science/Research
Classifier: Intended Audience :: Information Technology
Classifier: Topic :: Scientific/Engineering :: Information Analysis
Classifier: Topic :: Scientific/Engineering :: Physics
Classifier: Topic :: Multimedia :: Sound/Audio :: Analysis
Classifier: Programming Language :: Python :: 3
Classifier: License :: OSI Approved :: GNU General Public License v3 (GPLv3)
Classifier: Operating System :: OS Independent
Requires-Python: >=3.9
License-File: LICENSE
Requires-Dist: wheel
Requires-Dist: numpy
Requires-Dist: scipy >=0.18.0
Requires-Dist: matplotlib
